openbayestool/__init__.py
openbayestool/config.py
openbayestool/http_client.py
openbayestool/jwt_client.py
openbayestool/tracker.py
openbayestool/updater.py
openbayestool/version.py
openbayestool-0.3.2.dist-info/METADATA
openbayestool-0.3.2.dist-info/WHEEL
openbayestool-0.3.2.dist-info/top_level.txt
openbayestool-0.3.2.dist-info/RECORD
