Metadata-Version: 2.1
Name: openbayestool
Version: 0.3.2
Summary: Openbayes Service Tool
Home-page: https://openbayes.com
Author: Openbayes
License: UNKNOWN
Keywords: ml ai openbayes
Platform: UNKNOWN
Classifier: Intended Audience :: Developers
Classifier: Programming Language :: Python :: 3.6
Requires-Dist: requests (>=2.17.3)
